cmdshelper/__init__.py
cmdshelper/__main__.py
cmdshelper/helper.py
cmds_helper-0.1.1.dist-info/METADATA
cmds_helper-0.1.1.dist-info/WHEEL
cmds_helper-0.1.1.dist-info/entry_points.txt
cmds_helper-0.1.1.dist-info/licenses/LICENSE
cmds_helper-0.1.1.dist-info/RECORD
