Metadata-Version: 2.1
Name: cmds-helper
Version: 0.1.1
Summary: CLI CMD Command helper
Project-URL: Homepage, https://github.com/yotakeys/cmds-helper
Project-URL: Bug Tracker, https://github.com/yotakeys/cmds-helper/issues
Author-email: Keyisa Raihan <keyisakris@gmail.com>, Yoel Mountanus Sitorus <sclous2012@gmail.com>
License-File: LICENSE
Classifier: License :: OSI Approved :: MIT License
Classifier: Operating System :: OS Independent
Classifier: Programming Language :: Python :: 3
Requires-Python: >=3.7
